README.rst
setup.py
async_suds.egg-info/PKG-INFO
async_suds.egg-info/SOURCES.txt
async_suds.egg-info/dependency_links.txt
async_suds.egg-info/top_level.txt
asyncsuds/__init__.py
asyncsuds/argparser.py
asyncsuds/builder.py
asyncsuds/cache.py
asyncsuds/client.py
asyncsuds/metrics.py
asyncsuds/options.py
asyncsuds/plugin.py
asyncsuds/properties.py
asyncsuds/reader.py
asyncsuds/resolver.py
asyncsuds/servicedefinition.py
asyncsuds/serviceproxy.py
asyncsuds/soaparray.py
asyncsuds/store.py
asyncsuds/sudsobject.py
asyncsuds/version.py
asyncsuds/wsdl.py
asyncsuds/wsse.py
asyncsuds/bindings/__init__.py
asyncsuds/bindings/binding.py
asyncsuds/bindings/document.py
asyncsuds/bindings/multiref.py
asyncsuds/bindings/rpc.py
asyncsuds/mx/__init__.py
asyncsuds/mx/appender.py
asyncsuds/mx/basic.py
asyncsuds/mx/core.py
asyncsuds/mx/encoded.py
asyncsuds/mx/literal.py
asyncsuds/mx/typer.py
asyncsuds/sax/__init__.py
asyncsuds/sax/attribute.py
asyncsuds/sax/date.py
asyncsuds/sax/document.py
asyncsuds/sax/element.py
asyncsuds/sax/enc.py
asyncsuds/sax/parser.py
asyncsuds/sax/text.py
asyncsuds/transport/__init__.py
asyncsuds/transport/http_transport.py
asyncsuds/transport/https.py
asyncsuds/transport/options.py
asyncsuds/umx/__init__.py
asyncsuds/umx/attrlist.py
asyncsuds/umx/basic.py
asyncsuds/umx/core.py
asyncsuds/umx/encoded.py
asyncsuds/umx/typed.py
asyncsuds/xsd/__init__.py
asyncsuds/xsd/depsort.py
asyncsuds/xsd/doctor.py
asyncsuds/xsd/query.py
asyncsuds/xsd/schema.py
asyncsuds/xsd/sxbase.py
asyncsuds/xsd/sxbasic.py
asyncsuds/xsd/sxbuiltin.py