Metadata-Version: 1.1
Name: async-suds
Version: 1.0.6
Summary: Lightweight async SOAP client (Kamyar's fork)
Home-page: http://bitbucket.org/kamyar1979/async-suds
Author: Kamyar Inanloo
Author-email: kamyar1979@gmail.com
License: (specified using classifiers)
Download-URL: http://bitbucket.org/kamyar1979/async-suds/downloads/async-suds-1.0.6.tar.bz2
Keywords: SOAP,web,service,client
Platform: (specified using classifiers)
Classifier: Development Status :: 5 - Production/Stable
Classifier: Intended Audience :: Developers
Classifier: License :: OSI Approved :: GNU Library or Lesser General Public License (LGPL)
Classifier: Natural Language :: English
Classifier: Operating System :: OS Independent
Classifier: Programming Language :: Python
Classifier: Programming Language :: Python :: 3.3
Classifier: Programming Language :: Python :: 3.4
Classifier: Topic :: Internet
Obsoletes: suds
